ebraconys/__init__.py
ebraconys/math_utils.py
ebraconys/string_utils.py
ebraconys-0.1.3.dist-info/licenses/LICENSE
ebraconys-0.1.3.dist-info/METADATA
ebraconys-0.1.3.dist-info/WHEEL
ebraconys-0.1.3.dist-info/top_level.txt
ebraconys-0.1.3.dist-info/RECORD
