Metadata-Version: 2.4
Name: ebraconys
Version: 0.1.3
Summary: Utility functions for common Python tasks by Ebraconys Labs
Author-email: Ebraconys Team <ebraconys@gmail.com>
License: MIT
Project-URL: Homepage, https://github.com/ebraconys-labs/ebraconys
Project-URL: Repository, https://github.com/ebraconys-labs/ebraconys
Project-URL: Documentation, https://github.com/ebraconys-labs/ebraconys#readme
Project-URL: Bug Reports, https://github.com/ebraconys-labs/ebraconys/issues
Project-URL: Source Code, https://github.com/ebraconys-labs/ebraconys
Keywords: utilities,helpers,ebraconys-labs
Classifier: Development Status :: 4 - Beta
Classifier: Intended Audience :: Developers
Classifier: License :: OSI Approved :: MIT License
Classifier: Operating System :: OS Independent
Classifier: Programming Language :: Python :: 3
Classifier: Programming Language :: Python :: 3.8
Classifier: Programming Language :: Python :: 3.9
Classifier: Programming Language :: Python :: 3.10
Classifier: Programming Language :: Python :: 3.11
Classifier: Programming Language :: Python :: 3.12
License-File: LICENSE
Dynamic: license-file
